{"chhunks": [{"number": "14", "title": " Flowcharts Q8", "start": 0.0, "end ": 2.0, " text ": " Hi everyone, welcome to the supreme badge"}, {"number": "14", "title": " Flowcharts Q8", "start": 2.0, "end ": 4.0, " text ": " In this video we are going to print"}, {"number": "14", "title": " Flowcharts Q8", "start": 4.0, "end ": 6.0, " text ": " between 1 to n"}, {"number": "14", "title": " Flowcharts Q8", "start": 6.0, "end ": 8.0, " text ": " how many even numbers are there"}, {"number": "14", "title": " Flowcharts Q8", "start": 8.0, "end ": 10.0, " text ": " we are going to print this"}, {"number": "14", "title": " Flowcharts Q8", "start": 10.0, "end ": 12.0, " text ": " very good"}, {"number": "14", "title": " Flowcharts Q8", "start": 12.0, "end ": 14.0, " text ": " to print this"}, {"number": "14", "title": " Flowcharts Q8", "start": 14.0, "end ": 16.0, " text ": " what we need"}, {"number": "14", "title": " Flowcharts Q8", "start": 16.0, "end ": 18.0, " text ": " we need input before user"}, {"number": "14", "title": " Flowcharts Q8", "start": 18.0, "end ": 20.0, " text ": " we will take input n"}, {"number": "14", "title": " Flowcharts Q8", "start": 20.0, "end ": 22.0, " text ": " after that"}, {"number": "14", "title": " Flowcharts Q8", "start": 22.0, "end ": 24.0, " text ": " I will run a loop from 1 to n"}, {"number": "14", "title": " Flowcharts Q8", "start": 24.0, "end ": 26.0, " text ": " we need a loop"}, {"number": "14", "title": " Flowcharts Q8", "start": 26.0, "end ": 28.0, " text ": " here"}, {"number": "14", "title": " Flowcharts Q8", "start": 28.0, "end ": 30.0, " text ": " and we will print"}, {"number": "14", "title": " Flowcharts Q8", "start": 30.0, "end ": 32.0, " text ": " very good"}, {"number": "14", "title": " Flowcharts Q8", "start": 32.0, "end ": 34.0, " text ": " now let's see"}, {"number": "14", "title": " Flowcharts Q8", "start": 34.0, "end ": 36.0, " text ": " what is even number"}, {"number": "14", "title": " Flowcharts Q8", "start": 36.0, "end ": 38.0, " text ": " we know counting starts from 1,2,3,4"}, {"number": "14", "title": " Flowcharts Q8", "start": 38.0, "end ": 40.0, " text ": " 5,6,7"}, {"number": "14", "title": " Flowcharts Q8", "start": 40.0, "end ": 42.0, " text ": " what are even numbers"}, {"number": "14", "title": " Flowcharts Q8", "start": 42.0, "end ": 44.0, " text ": " those which are"}, {"number": "14", "title": " Flowcharts Q8", "start": 44.0, "end ": 46.0, " text ": " in 2 table"}, {"number": "14", "title": " Flowcharts Q8", "start": 46.0, "end ": 48.0, " text ": " divisible by 2 are even numbers"}, {"number": "14", "title": " Flowcharts Q8", "start": 48.0, "end ": 50.0, " text ": " 2"}, {"number": "14", "title": " Flowcharts Q8", "start": 50.0, "end ": 52.0, " text ": " 4"}, {"number": "14", "title": " Flowcharts Q8", "start": 52.0, "end ": 54.0, " text ": " 6"}, {"number": "14", "title": " Flowcharts Q8", "start": 54.0, "end ": 56.0, " text ": " so you know"}, {"number": "14", "title": " Flowcharts Q8", "start": 56.0, "end ": 58.0, " text ": " what is the first even number"}, {"number": "14", "title": " Flowcharts Q8", "start": 58.0, "end ": 60.0, " text ": " 2"}, {"number": "14", "title": " Flowcharts Q8", "start": 60.0, "end ": 62.0, " text ": " and next even number is 2 plus"}, {"number": "14", "title": " Flowcharts Q8", "start": 62.0, "end ": 64.0, " text ": " and next"}, {"number": "14", "title": " Flowcharts Q8", "start": 64.0, "end ": 66.0, " text ": " is 2 plus"}, {"number": "14", "title": " Flowcharts Q8", "start": 66.0, "end ": 68.0, " text ": " we know we have to start from 2"}, {"number": "14", "title": " Flowcharts Q8", "start": 68.0, "end ": 70.0, " text ": " and if I will do 2 plus"}, {"number": "14", "title": " Flowcharts Q8", "start": 70.0, "end ": 72.0, " text ": " then we will get another even number"}, {"number": "14", "title": " Flowcharts Q8", "start": 72.0, "end ": 74.0, " text ": " so now"}, {"number": "14", "title": " Flowcharts Q8", "start": 74.0, "end ": 76.0, " text ": " it is clear"}, {"number": "14", "title": " Flowcharts Q8", "start": 76.0, "end ": 78.0, " text ": " we have to start"}, {"number": "14", "title": " Flowcharts Q8", "start": 78.0, "end ": 80.0, " text ": " i from 2"}, {"number": "14", "title": " Flowcharts Q8", "start": 80.0, "end ": 82.0, " text ": " and it"}, {"number": "14", "title": " Flowcharts Q8", "start": 82.0, "end ": 84.0, " text ": " has to check a condition"}, {"number": "14", "title": " Flowcharts Q8", "start": 84.0, "end ": 86.0, " text ": " that i is"}, {"number": "14", "title": " Flowcharts Q8", "start": 86.0, "end ": 88.0, " text ": " less than or equal to n"}, {"number": "14", "title": " Flowcharts Q8", "start": 88.0, "end ": 90.0, " text ": " if yes, then I will print"}, {"number": "14", "title": " Flowcharts Q8", "start": 90.0, "end ": 92.0, " text ": " i"}, {"number": "14", "title": " Flowcharts Q8", "start": 92.0, "end ": 94.0, " text ": " else"}, {"number": "14", "title": " Flowcharts Q8", "start": 94.0, "end ": 96.0, " text ": " I will do"}, {"number": "14", "title": " Flowcharts Q8", "start": 96.0, "end ": 98.0, " text ": " i equal to i plus 2"}, {"number": "14", "title": " Flowcharts Q8", "start": 98.0, "end ": 100.0, " text ": " means I have to move ahead from 2 steps"}, {"number": "14", "title": " Flowcharts Q8", "start": 100.0, "end ": 102.0, " text ": " because next even number"}, {"number": "14", "title": " Flowcharts Q8", "start": 102.0, "end ": 104.0, " text ": " I will get after 2 plus"}, {"number": "14", "title": " Flowcharts Q8", "start": 104.0, "end ": 106.0, " text ": " very simple question"}, {"number": "14", "title": " Flowcharts Q8", "start": 106.0, "end ": 108.0, " text ": " let's make a brochure"}, {"number": "14", "title": " Flowcharts Q8", "start": 108.0, "end ": 110.0, " text ": " we will start"}, {"number": "14", "title": " Flowcharts Q8", "start": 110.0, "end ": 112.0, " text ": " we will start"}, {"number": "14", "title": " Flowcharts Q8", "start": 112.0, "end ": 114.0, " text ": " first we will"}, {"number": "14", "title": " Flowcharts Q8", "start": 114.0, "end ": 116.0, " text ": " read input"}, {"number": "14", "title": " Flowcharts Q8", "start": 122.0, "end ": 124.0, " text ": " we will read input"}, {"number": "14", "title": " Flowcharts Q8", "start": 124.0, "end ": 126.0, " text ": " n"}, {"number": "14", "title": " Flowcharts Q8", "start": 126.0, "end ": 128.0, " text ": " we will initialize a variable"}, {"number": "14", "title": " Flowcharts Q8", "start": 128.0, "end ": 130.0, " text ": " i equal to"}, {"number": "14", "title": " Flowcharts Q8", "start": 130.0, "end ": 132.0, " text ": " 2"}, {"number": "14", "title": " Flowcharts Q8", "start": 132.0, "end ": 134.0, " text ": " first even number is 2"}, {"number": "14", "title": " Flowcharts Q8", "start": 134.0, "end ": 136.0, " text ": " I have to check a condition"}, {"number": "14", "title": " Flowcharts Q8", "start": 136.0, "end ": 138.0, " text ": " because I have to run a loop"}, {"number": "14", "title": " Flowcharts Q8", "start": 138.0, "end ": 140.0, " text ": " is i less than or equal to"}, {"number": "14", "title": " Flowcharts Q8", "start": 140.0, "end ": 142.0, " text ": " n"}, {"number": "14", "title": " Flowcharts Q8", "start": 142.0, "end ": 144.0, " text ": " if yes"}, {"number": "14", "title": " Flowcharts Q8", "start": 144.0, "end ": 146.0, " text ": " then we will"}, {"number": "14", "title": " Flowcharts Q8", "start": 146.0, "end ": 148.0, " text ": " print"}, {"number": "14", "title": " Flowcharts Q8", "start": 148.0, "end ": 150.0, " text ": " i"}, {"number": "14", "title": " Flowcharts Q8", "start": 150.0, "end ": 152.0, " text ": " after printing i"}, {"number": "14", "title": " Flowcharts Q8", "start": 152.0, "end ": 154.0, " text ": " I will initialize"}, {"number": "14", "title": " Flowcharts Q8", "start": 154.0, "end ": 156.0, " text ": " i equal to"}, {"number": "14", "title": " Flowcharts Q8", "start": 156.0, "end ": 158.0, " text ": " i plus 2"}, {"number": "14", "title": " Flowcharts Q8", "start": 158.0, "end ": 160.0, " text ": " i will increment"}, {"number": "14", "title": " Flowcharts Q8", "start": 160.0, "end ": 162.0, " text ": " 2"}, {"number": "14", "title": " Flowcharts Q8", "start": 162.0, "end ": 164.0, " text ": " and then I will send it"}, {"number": "14", "title": " Flowcharts Q8", "start": 164.0, "end ": 166.0, " text ": " to this block"}, {"number": "14", "title": " Flowcharts Q8", "start": 166.0, "end ": 168.0, " text ": " ok"}, {"number": "14", "title": " Flowcharts Q8", "start": 168.0, "end ": 170.0, " text ": " if it doesn't happen"}, {"number": "14", "title": " Flowcharts Q8", "start": 170.0, "end ": 172.0, " text ": " i.e. condition of no"}, {"number": "14", "title": " Flowcharts Q8", "start": 172.0, "end ": 174.0, " text ": " then we will"}, {"number": "14", "title": " Flowcharts Q8", "start": 174.0, "end ": 176.0, " text ": " stop it"}, {"number": "14", "title": " Flowcharts Q8", "start": 176.0, "end ": 178.0, " text ": " ok"}, {"number": "14", "title": " Flowcharts Q8", "start": 178.0, "end ": 180.0, " text ": " very simple"}, {"number": "14", "title": " Flowcharts Q8", "start": 180.0, "end ": 182.0, " text ": " if I take value of n as 5"}, {"number": "14", "title": " Flowcharts Q8", "start": 182.0, "end ": 184.0, " text ": " then we will start with i equal to 2"}, {"number": "14", "title": " Flowcharts Q8", "start": 184.0, "end ": 186.0, " text ": " is 2 less than or equal to 5"}, {"number": "14", "title": " Flowcharts Q8", "start": 186.0, "end ": 188.0, " text ": " yes it is"}, {"number": "14", "title": " Flowcharts Q8", "start": 188.0, "end ": 190.0, " text ": " we will print 2"}, {"number": "14", "title": " Flowcharts Q8", "start": 190.0, "end ": 192.0, " text ": " and in 2"}, {"number": "14", "title": " Flowcharts Q8", "start": 192.0, "end ": 194.0, " text ": " we will do 2 plus"}, {"number": "14", "title": " Flowcharts Q8", "start": 194.0, "end ": 196.0, " text ": " and then 4"}, {"number": "14", "title": " Flowcharts Q8", "start": 196.0, "end ": 198.0, " text ": " 4 less than 5"}, {"number": "14", "title": " Flowcharts Q8", "start": 198.0, "end ": 200.0, " text ": " yes it is"}, {"number": "14", "title": " Flowcharts Q8", "start": 200.0, "end ": 202.0, " text ": " 4"}, {"number": "14", "title": " Flowcharts Q8", "start": 202.0, "end ": 204.0, " text ": " 4 plus"}, {"number": "14", "title": " Flowcharts Q8", "start": 204.0, "end ": 206.0, " text ": " 2 plus"}, {"number": "14", "title": " Flowcharts Q8", "start": 206.0, "end ": 208.0, " text ": " 6"}, {"number": "14", "title": " Flowcharts Q8", "start": 208.0, "end ": 210.0, " text ": " 6 less than or equal to 5"}, {"number": "14", "title": " Flowcharts Q8", "start": 210.0, "end ": 212.0, " text ": " yes it is"}, {"number": "14", "title": " Flowcharts Q8", "start": 212.0, "end ": 214.0, " text ": " and I will stop it"}, {"number": "14", "title": " Flowcharts Q8", "start": 214.0, "end ": 216.0, " text ": " very good"}, {"number": "14", "title": " Flowcharts Q8", "start": 216.0, "end ": 218.0, " text ": " we have printed odd number"}, {"number": "14", "title": " Flowcharts Q8", "start": 218.0, "end ": 220.0, " text ": " odd number is also simple"}, {"number": "14", "title": " Flowcharts Q8", "start": 220.0, "end ": 222.0, " text ": " you will start with i equal to 1"}, {"number": "14", "title": " Flowcharts Q8", "start": 222.0, "end ": 224.0, " text ": " very good"}, {"number": "14", "title": " Flowcharts Q8", "start": 224.0, "end ": 226.0, " text ": " let's move ahead"}, {"number": "14", "title": " Flowcharts Q8", "start": 226.0, "end ": 228.0, " text ": " its pseudocode will be very simple"}, {"number": "14", "title": " Flowcharts Q8", "start": 228.0, "end ": 230.0, " text ": " we will read n as i equal to 2"}, {"number": "14", "title": " Flowcharts Q8", "start": 230.0, "end ": 232.0, " text ": " I will initialize loop condition"}, {"number": "14", "title": " Flowcharts Q8", "start": 232.0, "end ": 234.0, " text ": " if I will print i equal to"}, {"number": "14", "title": " Flowcharts Q8", "start": 234.0, "end ": 236.0, " text ": " i plus 2"}, {"number": "14", "title": " Flowcharts Q8", "start": 236.0, "end ": 238.0, " text ": " and go to 3"}, {"number": "14", "title": " Flowcharts Q8", "start": 238.0, "end ": 240.0, " text ": " I have told it as loop"}, {"number": "14", "title": " Flowcharts Q8", "start": 240.0, "end ": 242.0, " text ": " it will be loop"}, {"number": "14", "title": " Flowcharts Q8", "start": 242.0, "end ": 244.0, " text ": " if it doesn't happen then condition will fail"}, {"number": "14", "title": " Flowcharts Q8", "start": 244.0, "end ": 246.0, " text ": " and when this condition fails"}, {"number": "14", "title": " Flowcharts Q8", "start": 246.0, "end ": 248.0, " text ": " then we will stop it"}, {"number": "14", "title": " Flowcharts Q8", "start": 248.0, "end ": 250.0, " text ": " this is the simple pseudocode"}, {"number": "14", "title": " Flowcharts Q8", "start": 250.0, "end ": 252.0, " text ": " see you in next video"}, {"number": "14", "title": " Flowcharts Q8", "start": 252.0, "end ": 254.0, " text ": " till then good bye"}], "text": " Hi everyone, welcome to the supreme badge In this video we are going to print between 1 to n how many even numbers are there we are going to print this very good to print this what we need we need input before user we will take input n after that I will run a loop from 1 to n we need a loop here and we will print very good now let's see what is even number we know counting starts from 1,2,3,4 5,6,7 what are even numbers those which are in 2 table divisible by 2 are even numbers 2 4 6 so you know what is the first even number 2 and next even number is 2 plus and next is 2 plus we know we have to start from 2 and if I will do 2 plus then we will get another even number so now it is clear we have to start i from 2 and it has to check a condition that i is less than or equal to n if yes, then I will print i else I will do i equal to i plus 2 means I have to move ahead from 2 steps because next even number I will get after 2 plus very simple question let's make a brochure we will start we will start first we will read input we will read input n we will initialize a variable i equal to 2 first even number is 2 I have to check a condition because I have to run a loop is i less than or equal to n if yes then we will print i after printing i I will initialize i equal to i plus 2 i will increment 2 and then I will send it to this block ok if it doesn't happen i.e. condition of no then we will stop it ok very simple if I take value of n as 5 then we will start with i equal to 2 is 2 less than or equal to 5 yes it is we will print 2 and in 2 we will do 2 plus and then 4 4 less than 5 yes it is 4 4 plus 2 plus 6 6 less than or equal to 5 yes it is and I will stop it very good we have printed odd number odd number is also simple you will start with i equal to 1 very good let's move ahead its pseudocode will be very simple we will read n as i equal to 2 I will initialize loop condition if I will print i equal to i plus 2 and go to 3 I have told it as loop it will be loop if it doesn't happen then condition will fail and when this condition fails then we will stop it this is the simple pseudocode see you in next video till then good bye"}